gotm/__init__.py
gotm/draox.py
gotm/xandor.py
gotm/offenders/__init__.py
gotm/offenders/one_zero_too_far.py
gotm-1.0.4.dist-info/LICENSE
gotm-1.0.4.dist-info/METADATA
gotm-1.0.4.dist-info/WHEEL
gotm-1.0.4.dist-info/top_level.txt
gotm-1.0.4.dist-info/RECORD
